colory_pprint.py
colory_pprint-1.5.1.dist-info/METADATA
colory_pprint-1.5.1.dist-info/WHEEL
colory_pprint-1.5.1.dist-info/licenses/LICENSE
colory_pprint-1.5.1.dist-info/RECORD
