Metadata-Version: 2.4
Name: colory-pprint
Version: 1.5.1
Summary: Colory PPrint is your new best friend when it comes to logging in Python—especially if you like your logs colorful, stylish, and super readable! Say goodbye to bland, hard-to-read logs and hello to clean, color-coded JSON logs with all the bells and whistles. Plus, it’s got your back when logging things that Python doesn't like to serialize.
Project-URL: Homepage, https://github.com/ruhiddin/colory-pprint
Project-URL: Documentation, https://github.com/ruhiddin/colory-pprint
Author-email: Ruhiddin Turdaliyev <niddihur@gmail.com>
License: MIT
License-File: LICENSE
Requires-Python: >=3.8
Requires-Dist: pytest>=8.3.5
Requires-Dist: termcolor
